<?xml version="1.0" encoding="ISO-8859-1"?>
<message_catalog package_key="forums" locale="it_IT" charset="ISO-8859-1">

  <msg key="Administer">Amministra</msg>
  <msg key="Administration">Amministrazione</msg>
  <msg key="Anonymous">Anonimo</msg>
  <msg key="approve">approva</msg>
  <msg key="Are_you_sure_you_want_to_delete_lt">Sei sicuro di voler cancellare questo messaggio e &lt;strong&gt;tutte le risposte collegate&lt;/strong&gt;? </msg>
  <msg key="Attach">Allega?</msg>
  <msg key="Attachments">Allegati</msg>
  <msg key="Author">Autore</msg>
  <msg key="Back_to_thread_label">Torna indietro&lt;/a&gt; a %forum.name%</msg>
  <msg key="Back_to_thread_link">&lt;a href=&quot;%thread_url%&quot;&gt;Torna indietro&lt;/a&gt; a %forum.name%</msg>
  <msg key="Body">Messaggio</msg>
  <msg key="by_Date">per Data</msg>
  <msg key="by_Forum">per Forum</msg>
  <msg key="Charter">Descrizione</msg>
  <msg key="closed">chiuso</msg>
  <msg key="Confirm">Confermi?</msg>
  <msg key="Confirm_Delete">Conferma Cancellazione</msg>
  <msg key="Confirm_Post_to_Forum">Conferma l'invio del messaggio:</msg>
  <msg key="Create_a_New_Forum">Crea un nuovo forum</msg>
  <msg key="Create_New_Forum">Crea un nuovo forum</msg>
  <msg key="delete">cancella</msg>
  <msg key="disable">disabilita</msg>
  <msg key="disable_it">Disabilita</msg>
  <msg key="disabled">disabilitati</msg>
  <msg key="Edit">Modifica</msg>
  <msg key="edit">modifica</msg>
  <msg key="Edit_again">Modifica ancora</msg>
  <msg key="Edit_forum">Modifica il forum</msg>
  <msg key="Edit_Message">Modifica il Messaggio:</msg>
  <msg key="Email">Email</msg>
  <msg key="email_alert_body_header">Il %posting_date%, %user_name% ha scritto:</msg>
  <msg key="Email_Message">Spedisci il messaggio:</msg>
  <msg key="Email_to_a_friend">Invia a un amico</msg>
  <msg key="enable">abilita</msg>
  <msg key="enable_it">abilitalo</msg>
  <msg key="enabled">abilitato</msg>
  <msg key="Entire_Thread">L'intera discussione</msg>
  <msg key="First_Post">Primo messaggio</msg>
  <msg key="Flat">Piatto</msg>
  <msg key="Format">Formato</msg>
  <msg key="Forum">Forum</msg>
  <msg key="Forum_1">Forum:</msg>
  <msg key="Forum_ID">ID Forum</msg>
  <msg key="forum_ID">ID Forum</msg>
  <msg key="Forum_Name">Nome del Forum</msg>
  <msg key="Forum_Posting">Invio messaggi al forum</msg>
  <msg key="ForumID">ForumID</msg>
  <msg key="Forums">Forum</msg>
  <msg key="Forums_Posting_hist_lt">Forum: Lista messaggi dell'utente</msg>
  <msg key="forward">Inoltra</msg>
  <msg key="Fwd">Fwd:</msg>
  <msg key="html">html</msg>
  <msg key="Last_Post">Ultimo messaggio</msg>
  <msg key="Last_post_in_subject">Ultimo messaggio in oggetto</msg>
  <msg key="lt_Email_a_copy_of_the_f">Invia per posta una copia di questo messaggio:</msg>
  <msg key="lt_First_post_in_subject">Primo messaggio in oggetto</msg>
  <msg key="lt_Forums_Administration">Amministrazione Forum</msg>
  <msg key="lt_Need_to_provide_a_mes">Occorre un messaggio per visualizzare</msg>
  <msg key="lt_need_to_provide_a_mes">Occorre un messaggio per visualizzare l'allegato!</msg>
  <msg key="lt_Note_that_you_are_alr">(Nota che tu hai già sottoscritto il forum per intero. Potresti ricevere notifiche doppie)</msg>
  <msg key="lt_Please_confirm_the_fo">Conferma il seguente messaggio:</msg>
  <msg key="lt_Please_enter_a_messag">Inserisci un messaggio</msg>
  <msg key="lt_Please_enter_a_subjec">Inserisci un oggetto</msg>
  <msg key="lt_Users_Can_Create_New_">Gli utenti possono aprire nuove discussioni</msg>
  <msg key="lt_Would_you_like_to_att">Vuoi associare un file in attach a questo messaggio?</msg>
  <msg key="lt_Would_you_like_to_sub">Vuoi ricevere un mail di notifica per eventuali risposte?</msg>
  <msg key="lt_You_either_have_to">Devi inviare un messaggio a un forum o rispondere a un altro messaggio</msg>
  <msg key="Manage">Gestisci</msg>
  <msg key="Manage_Forum">Gestione Forum:</msg>
  <msg key="ManageModerate">Gestisci/Modera</msg>
  <msg key="Message_ID">ID Messaggio</msg>
  <msg key="Moderate">Modera</msg>
  <msg key="moderated">moderato</msg>
  <msg key="Name">Nome</msg>
  <msg key="New_Forum">Nuovo Forum</msg>
  <msg key="No">No</msg>
  <msg key="No_Forums">Nessun Forum</msg>
  <msg key="No_Messages">Nessun Messaggio</msg>
  <msg key="No_Postings">Nessun invio</msg>
  <msg key="None">nessuno</msg>
  <msg key="One_Message">Un messaggio</msg>
  <msg key="One_Thread">Una discussione</msg>
  <msg key="open">aperta</msg>
  <msg key="Parameters">Parametri</msg>
  <msg key="parent_ID">parent ID</msg>
  <msg key="Pending">Pendente</msg>
  <msg key="Pending_Threads">Discussioni in attesa</msg>
  <msg key="Post">Messaggio</msg>
  <msg key="Post_a_Message">Invia un messaggio</msg>
  <msg key="Post_a_New_Message">Invia un nuovo messaggio</msg>
  <msg key="Post_a_Reply">Invia una risposta</msg>
  <msg key="Post_to_Forum">Invia un messaggio al Forum:</msg>
  <msg key="Posted">Data d'invio</msg>
  <msg key="Posted_by">Inviato da</msg>
  <msg key="Posting_Date">Data di invio</msg>
  <msg key="Posting_History">Elenco dei messaggi</msg>
  <msg key="Posting_history_for">Lista dei messaggi per l'utente</msg>
  <msg key="Posting_Policy">Politica sui messaggi pendente</msg>
  <msg key="Presentation">Presentazione</msg>
  <msg key="Preview">Anteprima</msg>
  <msg key="Re">Re:</msg>
  <msg key="reject">rifiuta</msg>
  <msg key="Rejected">Respinto</msg>
  <msg key="Replies">Risposte</msg>
  <msg key="reply">rispondi</msg>
  <msg key="Reply_to_first_post_in_thread">Rispondi al primo messaggio della discussione</msg>
  <msg key="Reply_to_first_post_on_page_label">Rispondi al primo messaggio su questa pagina</msg>
  <msg key="Search">Cerca:</msg>
  <msg key="Search_1">Cerca</msg>
  <msg key="Search_colon">Cerca:</msg>
  <msg key="Search_Forums">Cerca i Forum</msg>
  <msg key="Subject">Oggetto</msg>
  <msg key="Subscribe">Sottoscrivi?</msg>
  <msg key="text">testo</msg>
  <msg key="This_forum_is">Questo forum è</msg>
  <msg key="Threaded">Ramificato</msg>
  <msg key="Threads">Discussioni</msg>
  <msg key="View">Vedi</msg>
  <msg key="Yes">Sì</msg>
  <msg key="You_may">Puoi</msg>
  <msg key="Your_Note">Tua nota</msg>
</message_catalog>
