<?xml version="1.0" encoding="ISO-8859-1"?>
<message_catalog package_key="forums" locale="pt_PT" charset="ISO-8859-1">

  <msg key="Administer">Administrar</msg>
  <msg key="Administration">Administração</msg>
  <msg key="approve">aprovar</msg>
  <msg key="Are_you_sure_you_want_to_delete_lt">Tem a certeza de que quer eliminar esta mensagem e &lt;strong&gt;todas as respostas a esta&lt;/strong&gt;? </msg>
  <msg key="Attach">Anexar?</msg>
  <msg key="Attachments">Anexos:</msg>
  <msg key="Author">Autor</msg>
  <msg key="Body">Corpo</msg>
  <msg key="by_Date">por Data</msg>
  <msg key="by_Forum">por Forum</msg>
  <msg key="Charter">Descrição</msg>
  <msg key="closed">fechado</msg>
  <msg key="Confirm">Confirmar?</msg>
  <msg key="Confirm_Delete">Confirmar Eliminação:</msg>
  <msg key="Confirm_Post_to_Forum">Confirmar Envio de Mensagem para o Forum:</msg>
  <msg key="Create_a_New_Forum">Criar um Novo Forum</msg>
  <msg key="Create_New_Forum">Criar Novo Forum</msg>
  <msg key="delete">eliminar</msg>
  <msg key="disable">desactivar</msg>
  <msg key="disable_it">desactivá-lo</msg>
  <msg key="disabled">desactivado</msg>
  <msg key="Edit">Editar</msg>
  <msg key="edit">editar</msg>
  <msg key="Edit_forum">Editar forum</msg>
  <msg key="Edit_Message">Editar Mensagem:</msg>
  <msg key="Email">Enviar por Correio Electrónico</msg>
  <msg key="Email_Message">Enviar Mensagem por Correio Electrónico:</msg>
  <msg key="Email_to_a_friend">Enviar por correio electrónico a um amigo</msg>
  <msg key="enable">activar</msg>
  <msg key="enable_it">activá-lo</msg>
  <msg key="enabled">activado</msg>
  <msg key="Entire_Thread">Discussão Completa</msg>
  <msg key="Flat">Plano</msg>
  <msg key="Format">Formato</msg>
  <msg key="Forum">Forum</msg>
  <msg key="Forum_1">Forum:</msg>
  <msg key="Forum_ID">ID do Forum</msg>
  <msg key="forum_ID">ID do forum</msg>
  <msg key="Forum_Name">Nome do Forum</msg>
  <msg key="Forum_Posting">Envio de Mensagem para o Forum</msg>
  <msg key="ForumID">IDForum</msg>
  <msg key="Forums">Forums</msg>
  <msg key="Forums_Posting_hist_lt">Forums: Histórico de mensagens para</msg>
  <msg key="Fwd">Enc:</msg>
  <msg key="html">html</msg>
  <msg key="Last_Post">Última Mensagem</msg>
  <msg key="Last_post_in_subject">Última mensagem relativa a este assunto</msg>
  <msg key="lt_Email_a_copy_of_the_f">Enviar por correio electrónico uma cópia da seguinte mensagem:</msg>
  <msg key="lt_First_post_in_subject">Primeira mensagem relativa a este assunto</msg>
  <msg key="lt_Forums_Administration">Administração dos Forums</msg>
  <msg key="lt_Need_to_provide_a_mes">Necessita fornecer uma mensagem para apresentar.</msg>
  <msg key="lt_need_to_provide_a_mes">necessita fornecer uma mensagem para apresentar os anexos!</msg>
  <msg key="lt_Note_that_you_are_alr">(Note que já se encontra subscrito para o forum como um todo. Pode receber notificações duplicadas.)</msg>
  <msg key="lt_Please_confirm_the_fo">Por favor confirme a seguinte mensagem:</msg>
  <msg key="lt_Please_enter_a_messag">Por favor entre uma mensagem</msg>
  <msg key="lt_Please_enter_a_subjec">Por favor entre um assunto</msg>
  <msg key="lt_Users_Can_Create_New_">Os Utilizadores Podem Criar Novas Discussões</msg>
  <msg key="lt_Would_you_like_to_att">Gostaria de anexar um ficheiro a esta mensagem?</msg>
  <msg key="lt_Would_you_like_to_sub">Gostaria de subscrever-se para receber respostas?</msg>
  <msg key="lt_You_either_have_to">Deve enviar a mensagem para um forum ou em resposta a outra mensagem</msg>
  <msg key="Manage">Gerir</msg>
  <msg key="Manage_Forum">Gerir Forum:</msg>
  <msg key="ManageModerate">Gerir/Moderar</msg>
  <msg key="Message_ID">ID da Mensagem</msg>
  <msg key="moderated">moderado</msg>
  <msg key="Name">Nome</msg>
  <msg key="New_Forum">Novo Forum</msg>
  <msg key="No">Não</msg>
  <msg key="No_Forums">Não há Forums</msg>
  <msg key="No_Messages">Não há Mensagens</msg>
  <msg key="No_Postings">Não há mensagens enviadas.</msg>
  <msg key="None">Nenhum</msg>
  <msg key="One_Message">Uma Mensagem</msg>
  <msg key="One_Thread">Uma Discussão</msg>
  <msg key="open">aberto</msg>
  <msg key="parent_ID">ID do pai</msg>
  <msg key="Pending_Threads">Discussões Pendentes</msg>
  <msg key="Post_a_Message">Enviar uma Mensagem</msg>
  <msg key="Post_a_New_Message">Enviar uma Nova Mensagem</msg>
  <msg key="Post_a_Reply">Enviar uma Resposta</msg>
  <msg key="Post_to_Forum">Enviar mensagem para o Forum:</msg>
  <msg key="Posted">Enviada</msg>
  <msg key="Posting_Date">Data de Envio</msg>
  <msg key="Posting_History">Histórico das Mensagens Enviadas</msg>
  <msg key="Posting_history_for">Histórico das mensagens enviadas para</msg>
  <msg key="Posting_Policy">Politica de envio de mensagens</msg>
  <msg key="Presentation">Apresentação</msg>
  <msg key="Re">Res:</msg>
  <msg key="reject">rejeitar</msg>
  <msg key="Replies">Respostas</msg>
  <msg key="reply">responder</msg>
  <msg key="Search">Pesquisar:</msg>
  <msg key="Search_1">Pesquisar</msg>
  <msg key="Search_colon">Pesquisar:</msg>
  <msg key="Search_Forums">Pesquisar Forums</msg>
  <msg key="Subject">Assunto</msg>
  <msg key="Subscribe">Subscrever?</msg>
  <msg key="text">texto</msg>
  <msg key="This_forum_is">Este forum é</msg>
  <msg key="Threaded">Por Discussões</msg>
  <msg key="Threads">Discussões</msg>
  <msg key="View">Ver</msg>
  <msg key="Yes">Sim</msg>
  <msg key="You_may">Pode</msg>
  <msg key="Your_Note">Sua Nota</msg>
</message_catalog>
