<wddxPacket version="1.0"><header /><data><struct><var name="messageKey"><string>getDictionary</string></var><var name="messageType"><number>3</number></var><var name="messageValue"><array length="29"><struct><var name="key"><string>ws_dlg_title</string></var><var name="value"><string>Workspace</string></var><var name="description"><string>0</string></var></struct><struct><var name="key"><string>ws_dlg_ok_button</string></var><var name="value"><string>OK</string></var><var name="description"><string>1</string></var></struct><struct><var name="key"><string>ws_dlg_cancel_button</string></var><var name="value"><string>Cancel</string></var><var name="description"><string>2</string></var></struct><struct><var name="key"><string>trans_dlg_title</string></var><var name="value"><string>Transition</string></var><var name="description"><string>Title for the transition properties dialog</string></var></struct><struct><var name="description"><string>OK Button on transition dialog</string></var><var name="value"><string>OK</string></var><var name="key"><string>trans_dlg_ok</string></var></struct><struct><var name="description"><string>Cancel button on transition dialog</string></var><var name="value"><string>Cancel</string></var><var name="key"><string>trans_dlg_cancel</string></var></struct><struct><var name="key"><string>prefs_dlg_title</string></var><var name="value"><string>Preferences</string></var><var name="description"><string>4</string></var></struct><struct><var name="key"><string>prefs_dlg_theme_lbl</string></var><var name="value"><string>Theme</string></var><var name="description"><string>8</string></var></struct><struct><var name="key"><string>prefs_dlg_ok</string></var><var name="value"><string>OK</string></var><var name="description"><string>5</string></var></struct><struct><var name="key"><string>prefs_dlg_lng_lbl</string></var><var name="value"><string>Language</string></var><var name="description"><string>7</string></var></struct><struct><var name="key"><string>prefs_dlg_cancel</string></var><var name="value"><string>Cancel</string></var><var name="description"><string>6</string></var></struct><struct><var name="key"><string>mnu_tools_trans</string></var><var name="value"><string>Draw Transition</string></var><var name="description"><string>14</string></var></struct><struct><var name="key"><string>mnu_tools_prefs</string></var><var name="value"><string>Preferences</string></var><var name="description"><string>16</string></var></struct><struct><var name="key"><string>mnu_tools_prefs</string></var><var name="value"><string>Preferences</string></var><var name="description"><string>21</string></var></struct><struct><var name="key"><string>mnu_tools_opt</string></var><var name="value"><string>Draw Optional</string></var><var name="description"><string>15</string></var></struct><struct><var name="key"><string>mnu_tools</string></var><var name="value"><string>Tools</string></var><var name="description"><string>18</string></var></struct><struct><var name="key"><string>mnu_help_abt</string></var><var name="value"><string>About</string></var><var name="description"><string>20</string></var></struct><struct><var name="key"><string>mnu_help</string></var><var name="value"><string>Help</string></var><var name="description"><string>19</string></var></struct><struct><var name="key"><string>mnu_file_save</string></var><var name="value"><string>Save</string></var><var name="description"><string>13</string></var></struct><struct><var name="key"><string>mnu_file_revert</string></var><var name="value"><string>Revert</string></var><var name="description"><string>11</string></var></struct><struct><var name="key"><string>mnu_file_open</string></var><var name="value"><string>Open</string></var><var name="description"><string>10</string></var></struct><struct><var name="key"><string>mnu_file_new</string></var><var name="value"><string>New</string></var><var name="description"><string>9</string></var></struct><struct><var name="key"><string>mnu_file_close</string></var><var name="value"><string>Close</string></var><var name="description"><string>12</string></var></struct><struct><var name="key"><string>mnu_file</string></var><var name="value"><string>File</string></var><var name="description"><string>17</string></var></struct><struct><var name="key"><string>synch_act_lbl</string></var><var name="value"><string>Synchronise</string></var><var name="description"><string>Used as a label for the Synch Gate Activity Type</string></var></struct><struct><var name="key"><string>sched_act_lbl</string></var><var name="value"><string>Schedule</string></var><var name="description"><string>Label for schedule gate activity</string></var></struct><struct><var name="key"><string>perm_act_lbl</string></var><var name="value"><string>Permission</string></var><var name="description"><string>Label for permission gate activity</string></var></struct><struct><var name="key"><string>trans_dlg_gate</string></var><var name="value"><string>Synchronisation</string></var><var name="description"><string>Header for the transition props dialog</string></var></struct><struct><var name="key"><string>trans_dlg_gatetypecmb</string></var><var name="value"><string>Type</string></var><var name="description"><string>Gate type combo label</string></var></struct></array></var></struct></data></wddxPacket>