<wddxPacket version="1.0"><header/><data><struct><var name="messageKey"><string>getDictionary</string></var><var name="messageType"><number>3</number></var><var name="messageValue"><array length="190"><struct><var name="key"><string>ls_win_editclass_save_btn</string></var><var name="value"><string>Kaydet</string></var><var name="description"><string>Save button on Edit Class popup</string></var></struct><struct><var name="key"><string>about_popup_license_lbl</string></var><var name="value"><string>Bu program üzretsiz bir yazılımdır; dağıtabilir ve/veya Free Softvare Foundation tarafından yayınlanan GNU General Public Licence version 2 şartları altında değiştirebilirsiniz. </string></var><var name="description"><string>Label displaying the license statement in the About dialog.</string></var></struct><struct><var name="key"><string>stream_url</string></var><var name="value"><string>http://{0}foundation.org</string></var><var name="description"><string>URL address for the application stream.</string></var></struct><struct><var name="key"><string>learner_viewJournals_btn_tooltip</string></var><var name="value"><string>Öğrencilerin kaydettiği günlük mesajlarının tümünü göster.</string></var><var name="description"><string>tool tip message for Journal Entries button used on Learner tab to view all journal entires for the lesson.</string></var></struct><struct><var name="key"><string>branch_mapping_dlg_condition_col_lbl</string></var><var name="value"><string>Koşul</string></var><var name="description"><string>Column heading for showing condition description of the mapping.</string></var></struct><struct><var name="key"><string>learner_exportPortfolio_btn_tooltip</string></var><var name="value"><string>Bu öğrencinin portfolyosunu dışa aktarıp bilgisayarınıza kaydeder.</string></var><var name="description"><string>tool tip message for exportportfolio button for individual learner to export portfolio for the respective learner and save to it in on user computer for future reference</string></var></struct><struct><var name="key"><string>class_exportPortfolio_btn_tooltip</string></var><var name="value"><string>Dersin portfolyosunu dışa aktarır ve ileride kullanılmak üzere bilgisayarınıza kaydeder.</string></var><var name="description"><string>tool tip message for exportportfolio button next to refresh button to export class portfolio and save in on user computer</string></var></struct><struct><var name="key"><string>cv_design_unsaved_live_edit</string></var><var name="value"><string>Kaydedilmeyen değişiklikler otomatik olarak kaydedilecek. Ekle/birleştir ile devam etmek istiyor musunuz?</string></var><var name="description"><string>Confirm alert message displayed when doing an insert/merge to a modified design in Live Edit.</string></var></struct><struct><var name="key"><string>al_validation_schtime</string></var><var name="value"><string>Lütfen geçerli bir zaman giriniz.</string></var><var name="description"><string>Alert message when user enters an invalid time for schedule start</string></var></struct><struct><var name="key"><string>view_competences_dlg</string></var><var name="value"><string>Yetkileri görüntüle</string></var><var name="description"><string>Allows you to view all the competences within a learning design</string></var></struct><struct><var name="key"><string>view_act_mapped_competences</string></var><var name="value"><string>Haritalanmış yetkileri görüntüle</string></var><var name="description"><string>Allows you to view competences mapped to a particular activity</string></var></struct><struct><var name="key"><string>ccm_monitor_view_condition_mappings</string></var><var name="value"><string>Koşullara olan dallanmaları göster</string></var><var name="description"><string>Label for Custom Context View Condition Mappings</string></var></struct><struct><var name="key"><string>ccm_monitor_view_group_mappings</string></var><var name="value"><string>Grup dallanmalarını göster</string></var><var name="description"><string>Label for Custom Context View Group Mappings</string></var></struct><struct><var name="key"><string>ls_manage_learners_btn</string></var><var name="value"><string>Öğrenci görüntüle</string></var><var name="description"><string>View learners button - Lesson details (manage section)</string></var></struct><struct><var name="key"><string>ls_win_learners_title</string></var><var name="value"><string>Öğrenenleri görüntüle</string></var><var name="description"><string>View learners window title</string></var></struct><struct><var name="key"><string>mnu_view</string></var><var name="value"><string>Görünüm</string></var><var name="description"><string>Menu bar View</string></var></struct><struct><var name="key"><string>mv_search_index_view_btn_lbl</string></var><var name="value"><string>Dizin görünümü</string></var><var name="description"><string>When the user clicks this button, they will be returning from the search view to the index view. It will once again allow them to view all the available pages, and navigate to them directly. This button is only visible when the user is in the search view.</string></var></struct><struct><var name="key"><string>al_activity_view_competence_mappings_invalid</string></var><var name="value"><string>Yetkileri gmrüntülemeden önce bir etkinlik seçtiğinizden emin olunuz.</string></var><var name="description"><string>Warning that appears when no activity is selected when the user tries to view competence mappings</string></var></struct><struct><var name="key"><string>current_act_tooltip</string></var><var name="value"><string>Öğrencinin şimdiki etkinliğine katılımını gözlemek için çift tıklayınız.</string></var><var name="description"><string>tool tip message for current activity icon</string></var></struct><struct><var name="key"><string>completed_act_tooltip</string></var><var name="value"><string>Öğrencilerin tamamladığı etkinlikleri görmek için çift tıklayınız.</string></var><var name="description"><string>tool tip message for completed activity icon</string></var></struct><struct><var name="key"><string>al_cancel</string></var><var name="value"><string>İptal</string></var><var name="description"><string>To Confirm title for LFError</string></var></struct><struct><var name="key"><string>ws_dlg_cancel_button</string></var><var name="value"><string>İptal</string></var><var name="description"><string>2</string></var></struct><struct><var name="key"><string>learner_exportPortfolio_btn</string></var><var name="value"><string>Portfolyo kaydet</string></var><var name="description"><string>Label for Export Portfolio used both on learners tab to export learner data and monitor tab to export class data</string></var></struct><struct><var name="key"><string>ls_manage_learnerExpp_lbl</string></var><var name="value"><string>Öğrenci için portfolyo dışa aktarmayı etkinleştir</string></var><var name="description"><string>Label for Enable export portfolio for Learner</string></var></struct><struct><var name="key"><string>ls_confirm_expp_enabled</string></var><var name="value"><string>Portfolyo dışa aktarma etkinleştirildi.</string></var><var name="description"><string>Confirmation message on enabling export portfolio for learners</string></var></struct><struct><var name="key"><string>ls_confirm_expp_disabled</string></var><var name="value"><string>Portfolyo dışa aktarmayı devreden çıkar</string></var><var name="description"><string>Confirmation message on disabling export portfolio for learners</string></var></struct><struct><var name="key"><string>ls_win_editclass_organisation_lbl</string></var><var name="value"><string>Organizasyon</string></var><var name="description"><string>Heading for Organisation tree on Edit Class popup</string></var></struct><struct><var name="key"><string>al_alert</string></var><var name="value"><string>Uyarı</string></var><var name="description"><string>Generic title for Alert window</string></var></struct><struct><var name="key"><string>al_confirm</string></var><var name="value"><string>Onayla</string></var><var name="description"><string>To Confirm title for LFError</string></var></struct><struct><var name="key"><string>app_chk_langload</string></var><var name="value"><string>Dil bileşenleri yüklenmedi</string></var><var name="description"><string>message for unsuccessful language loading</string></var></struct><struct><var name="key"><string>app_chk_themeload</string></var><var name="value"><string>Tema bileşenleri yüklenmedi</string></var><var name="description"><string>message for unsuccessful theme loading</string></var></struct><struct><var name="key"><string>app_fail_continue</string></var><var name="value"><string>Uygulamaya devam edilemiyor. Destek için iletişime geçiniz.</string></var><var name="description"><string>message if application cannot continue due to any error</string></var></struct><struct><var name="key"><string>db_datasend_confirm</string></var><var name="value"><string>Sunucuya gönderdiğiniz veri için teşekkürler.</string></var><var name="description"><string>Message when user sucessfully dumps data to the server</string></var></struct><struct><var name="key"><string>mnu_edit</string></var><var name="value"><string>Düzenle</string></var><var name="description"><string>Menu bar Edit</string></var></struct><struct><var name="key"><string>mnu_edit_copy</string></var><var name="value"><string>Kopyala</string></var><var name="description"><string>Menu bar Edit &amp;gt; Copy</string></var></struct><struct><var name="key"><string>mnu_edit_cut</string></var><var name="value"><string>Kes</string></var><var name="description"><string>Menu bar Edit &amp;gt; Cut</string></var></struct><struct><var name="key"><string>mnu_edit_paste</string></var><var name="value"><string>Yapıştır</string></var><var name="description"><string>Menu bar Edit &amp;gt; Paste</string></var></struct><struct><var name="key"><string>mnu_file</string></var><var name="value"><string>Dosya</string></var><var name="description"><string>Menu bar File</string></var></struct><struct><var name="key"><string>mnu_file_refresh</string></var><var name="value"><string>Yenile</string></var><var name="description"><string>Menu bar Refresh</string></var></struct><struct><var name="key"><string>mnu_file_editclass</string></var><var name="value"><string>Ders düzenle</string></var><var name="description"><string>Menu bar Edit Class</string></var></struct><struct><var name="key"><string>mnu_file_start</string></var><var name="value"><string>Başla</string></var><var name="description"><string>Menu bar Start</string></var></struct><struct><var name="key"><string>mnu_help</string></var><var name="value"><string>Yardım</string></var><var name="description"><string>Menu bar Help</string></var></struct><struct><var name="key"><string>mnu_help_abt</string></var><var name="value"><string>Hakkında</string></var><var name="description"><string>Menu bar About</string></var></struct><struct><var name="key"><string>perm_act_lbl</string></var><var name="value"><string>İzin</string></var><var name="description"><string>Label for permission gate activity</string></var></struct><struct><var name="key"><string>mv_search_not_found_msg</string></var><var name="value"><string>{0} bulunamadı</string></var><var name="description"><string>This message appears when the search does not find any learners whose names contain the search parameter.</string></var></struct><struct><var name="key"><string>mv_search_current_page_lbl</string></var><var name="value"><string>Sayfa {0}/{1}</string></var><var name="description"><string>{0} is the page we are on now and {1} is the number of pages</string></var></struct><struct><var name="key"><string>mv_search_go_btn_lbl</string></var><var name="value"><string>Git</string></var><var name="description"><string>If the learner entered text into the index/search field, clicking this button will search all started learners names for the text they entered, otherwise if they entered a number and clicked go. It will show the contents of the page, whose number they entered.</string></var></struct><struct><var name="key"><string>ls_seq_status_moderation</string></var><var name="value"><string>Etkinlik yönet</string></var><var name="description"><string>Displayed when we want the Teacher to moderate an activitiy (for example a chat room)</string></var></struct><struct><var name="key"><string>ls_seq_status_perm_gate</string></var><var name="value"><string>İzin kapısı</string></var><var name="description"><string>A type of Gate Activity where progress depends on permission from a Teacher</string></var></struct><struct><var name="key"><string>ls_seq_status_choose_grouping</string></var><var name="value"><string>Gruplamayı seç</string></var><var name="description"><string>Allows the Teacher to add the learners to chosen groups</string></var></struct><struct><var name="key"><string>ls_seq_status_system_gate</string></var><var name="value"><string>Sistem kapısı</string></var><var name="description"><string>A System Gate is a stop point that can be controlled by time setting or user control</string></var></struct><struct><var name="key"><string>ws_Root</string></var><var name="value"><string>Ana dizin</string></var><var name="description"><string>Root folder title for workspace</string></var></struct><struct><var name="key"><string>ws_tree_mywsp</string></var><var name="value"><string>Çalışma Alanım</string></var><var name="description"><string>The root level of the tree</string></var></struct><struct><var name="key"><string>sys_error_msg_start</string></var><var name="value"><string>Bir sistem hatası oluştu.</string></var><var name="description"><string>Common System error message starting line</string></var></struct><struct><var name="key"><string>sys_error</string></var><var name="value"><string>Sistem hatası</string></var><var name="description"><string>System Error elert window title</string></var></struct><struct><var name="key"><string>mnu_file_exit</string></var><var name="value"><string>Çıkış</string></var><var name="description"><string>Menu bar Exit</string></var></struct><struct><var name="key"><string>mnu_go</string></var><var name="value"><string>Git</string></var><var name="description"><string>Menu bar Go</string></var></struct><struct><var name="key"><string>mnu_go_lesson</string></var><var name="value"><string>Ders</string></var><var name="description"><string>Menu bar  Go to Lesson Tab</string></var></struct><struct><var name="key"><string>refresh_btn</string></var><var name="value"><string>Yenile</string></var><var name="description"><string>Refresh button</string></var></struct><struct><var name="key"><string>help_btn</string></var><var name="value"><string>Yardım</string></var><var name="description"><string>Help button</string></var></struct><struct><var name="key"><string>mtab_lesson</string></var><var name="value"><string>Ders</string></var><var name="description"><string>Monitor Lesson details tab</string></var></struct><struct><var name="key"><string>mtab_seq</string></var><var name="value"><string>Sıralama</string></var><var name="description"><string>Monitor Sequence tab</string></var></struct><struct><var name="key"><string>ls_status_lbl</string></var><var name="value"><string>Durum</string></var><var name="description"><string>Status label - Lesson details</string></var></struct><struct><var name="key"><string>ls_manage_start_lbl</string></var><var name="value"><string>Başla</string></var><var name="description"><string>Start managing label - Lesson details</string></var></struct><struct><var name="key"><string>ls_manage_editclass_btn</string></var><var name="value"><string>Sınıfı düzenle</string></var><var name="description"><string>Edit class button - Lesson details (manage section)</string></var></struct><struct><var name="key"><string>ls_manage_apply_btn</string></var><var name="value"><string>Uygula</string></var><var name="description"><string>Status Apply button - Lesson details (manage section)</string></var></struct><struct><var name="key"><string>ls_manage_start_btn</string></var><var name="value"><string>Şimdi başla</string></var><var name="description"><string>Start immediately button - Lesson details (manage section)</string></var></struct><struct><var name="key"><string>ls_manage_date_lbl</string></var><var name="value"><string>Tarih</string></var><var name="description"><string>Date field title - Lesson details (manage section)</string></var></struct><struct><var name="key"><string>ls_manage_status_cmb</string></var><var name="value"><string>Durum seç</string></var><var name="description"><string>Status combo top  (index) item - Lesson details (manage section)</string></var></struct><struct><var name="key"><string>ls_status_cmb_activate</string></var><var name="value"><string>Etkinleştir</string></var><var name="description"><string>Lesson status option - Activate</string></var></struct><struct><var name="key"><string>ls_status_cmb_disable</string></var><var name="value"><string>Pasif</string></var><var name="description"><string>Lesson status option - Disable (suspend)</string></var></struct><struct><var name="key"><string>ls_status_cmb_enable</string></var><var name="value"><string>Aktif</string></var><var name="description"><string>Lesson status option - Enable (make active/unsuspend)</string></var></struct><struct><var name="key"><string>ls_status_cmb_archive</string></var><var name="value"><string>Arşiv</string></var><var name="description"><string>Lesson status option - Archive</string></var></struct><struct><var name="key"><string>ls_status_active_lbl</string></var><var name="value"><string>Oluşturuldu ancak başlatılmadı</string></var><var name="description"><string>Current status description if active (enabled)</string></var></struct><struct><var name="key"><string>ls_status_disabled_lbl</string></var><var name="value"><string>Pasif</string></var><var name="description"><string>Current status description if suspended (disabled)</string></var></struct><struct><var name="key"><string>ls_status_archived_lbl</string></var><var name="value"><string>Arşivlendi</string></var><var name="description"><string>Current status description if archvied</string></var></struct><struct><var name="key"><string>ls_status_started_lbl</string></var><var name="value"><string>Başladı</string></var><var name="description"><string>Current status description if started (enabled)</string></var></struct><struct><var name="key"><string>ls_win_editclass_title</string></var><var name="value"><string>Sınıfı düzenle</string></var><var name="description"><string>Edit class window title</string></var></struct><struct><var name="key"><string>ls_win_learners_close_btn</string></var><var name="value"><string>Kapat</string></var><var name="description"><string>Close button on View Learners popup</string></var></struct><struct><var name="key"><string>ls_win_editclass_learners_lbl</string></var><var name="value"><string>Öğrenciler</string></var><var name="description"><string>Heading for Learners list on the Edit Class popup</string></var></struct><struct><var name="key"><string>ls_win_learners_heading_lbl</string></var><var name="value"><string>Sınıftaki öğrenciler</string></var><var name="description"><string>Heading on View Learners window panel.</string></var></struct><struct><var name="key"><string>td_desc_heading</string></var><var name="value"><string>Gelişmiş kontroller</string></var><var name="description"><string>Todo tab description heading</string></var></struct><struct><var name="key"><string>opt_activity_title</string></var><var name="value"><string>Seçmeli Etkinlik</string></var><var name="description"><string>Title for Optional Activity on canvas (monitoring)</string></var></struct><struct><var name="key"><string>lbl_num_activities</string></var><var name="value"><string>{0} - Etkinlikler</string></var><var name="description"><string>Number of child activities for Complex activity shown on canvas.</string></var></struct><struct><var name="key"><string>ls_manage_txt</string></var><var name="value"><string>Dersi yönet</string></var><var name="description"><string>Heading for Management section of Lesson Tab</string></var></struct><struct><var name="key"><string>ls_tasks_txt</string></var><var name="value"><string>Yapılması gereken görevler</string></var><var name="description"><string>Heading for Required Tasks (todo section of Lesson tab)</string></var></struct><struct><var name="key"><string>td_goContribute_btn</string></var><var name="value"><string>Git</string></var><var name="description"><string>Go button on contribute entry item</string></var></struct><struct><var name="key"><string>al_send</string></var><var name="value"><string>Gönder</string></var><var name="description"><string>Send button label on the system error dialog</string></var></struct><struct><var name="key"><string>al_validation_schstart</string></var><var name="value"><string>Tarih seçilmedi. Lütfen tarih ve zaman seçiniz.</string></var><var name="description"><string>Message when no date is selected for starting a lesson by schedule.</string></var></struct><struct><var name="key"><string>title_sequencetab_endGate</string></var><var name="value"><string>Bitiren öğrenciler</string></var><var name="description"><string>Title for end gate bar shown at the bottom of monitor tab where user can drop a learner to force complete to the end of lesson</string></var></struct><struct><var name="key"><string>ls_learnerURL_lbl</string></var><var name="value"><string>Öğrenci URL'si</string></var><var name="description"><string>Learner URL:</string></var></struct><struct><var name="key"><string>goContribute_btn_tooltip</string></var><var name="value"><string>Bu görevi şimdi tamamla</string></var><var name="description"><string>tool tip message for go button in required tasks list in lesson tab</string></var></struct><struct><var name="key"><string>help_btn_tooltip</string></var><var name="value"><string>Yardım</string></var><var name="description"><string>tool tip message for help button in toolbar</string></var></struct><struct><var name="key"><string>ls_manage_editclass_btn_tooltip</string></var><var name="value"><string>Bu derse kayırlı öğrencileri düzenler ve izler.</string></var><var name="description"><string>tool tip message for the edit class button in lesson tab under manage lesson section</string></var></struct><struct><var name="key"><string>ls_manage_learners_btn_tooltip</string></var><var name="value"><string>Bu derse kayıtlı öğrencileri gösterir.</string></var><var name="description"><string>tool tip message for the view learners button in lesson tab under manage lesson section</string></var></struct><struct><var name="key"><string>ls_class_lbl</string></var><var name="value"><string>Sınıf</string></var><var name="description"><string>Class label - Lesson details</string></var></struct><struct><var name="key"><string>ls_manage_class_lbl</string></var><var name="value"><string>Sınıf</string></var><var name="description"><string>Class managing label - Lesson details</string></var></struct><struct><var name="key"><string>ls_manage_status_lbl</string></var><var name="value"><string>Durum değiştir</string></var><var name="description"><string>Status managing label - Lesson details</string></var></struct><struct><var name="key"><string>ls_win_editclass_cancel_btn</string></var><var name="value"><string>İptal</string></var><var name="description"><string>Cancel button on Edit Class popup</string></var></struct><struct><var name="key"><string>ls_duration_lbl</string></var><var name="value"><string>Geçen zaman</string></var><var name="description"><string>Elapsed duration of lesson - Lesson details</string></var></struct><struct><var name="key"><string>ccm_monitor_activityhelp</string></var><var name="value"><string>Etkinlik yardımını izle</string></var><var name="description"><string>Label for Custom Context Monitor Activity Help</string></var></struct><struct><var name="key"><string>learner_viewJournals_btn</string></var><var name="value"><string>Günlük mesajları</string></var><var name="description"><string>Label for Journal Entries button used on Learners tab to view all journal entires for the lesson.</string></var></struct><struct><var name="key"><string>learners_group_name</string></var><var name="value"><string>{0} öğrenci</string></var><var name="description"><string>Group name for the class's learners group.</string></var></struct><struct><var name="key"><string>ls_remove_confirm_msg</string></var><var name="value"><string>Bu dersi kaldırmayı seçtiniz. Bu işlemi tekrar geri lamazsınız. devam etmek istiyor musunuz?</string></var><var name="description"><string>remove confirm msg</string></var></struct><struct><var name="key"><string>continue_btn</string></var><var name="value"><string>Devam et</string></var><var name="description"><string>Continue button label</string></var></struct><struct><var name="key"><string>msg_bubble_check_action_lbl</string></var><var name="value"><string>Kontrol ediliyor...</string></var><var name="description"><string>Label displayed when checking availability of lesson.</string></var></struct><struct><var name="key"><string>msg_bubble_failed_action_lbl</string></var><var name="value"><string>Gerçekleştirilemedi, tekrar deneyiniz.</string></var><var name="description"><string>Label displayed when check failed i.e. lesson is still locked.</string></var></struct><struct><var name="key"><string>branch_mapping_dlg_branch_col_lbl</string></var><var name="value"><string>Dallanma</string></var><var name="description"><string>Column heading for showing sequence name of the mapping.</string></var></struct><struct><var name="key"><string>branch_mapping_dlg_group_col_lbl</string></var><var name="value"><string>Grup</string></var><var name="description"><string>Column heading for showing group name of the mapping.</string></var></struct><struct><var name="key"><string>mnu_go_sequence</string></var><var name="value"><string>Sıralama</string></var><var name="description"><string>Menu bar Go to Sequence Tab</string></var></struct><struct><var name="key"><string>cv_activity_helpURL_undefined</string></var><var name="value"><string>{0}'ın yardım sayfası bulunamıyor.</string></var><var name="description"><string>Alert message when a tool activity has no help url defined.</string></var></struct><struct><var name="key"><string>al_doubleclick_todoactivity</string></var><var name="value"><string>Üzgünüm, öğrenci {0} henüz etkinliğe erişmedi</string></var><var name="description"><string>alert message when user double click on the todo activity in the sequence under learner tab</string></var></struct><struct><var name="key"><string>ls_status_cmb_remove</string></var><var name="value"><string>Kaldır</string></var><var name="description"><string>Lesson status option - Remove</string></var></struct><struct><var name="key"><string>ls_status_removed_lbl</string></var><var name="value"><string>Kaldırıldı</string></var><var name="description"><string>Current status description if deleted (removed) lesson.</string></var></struct><struct><var name="key"><string>al_yes</string></var><var name="value"><string>Evet</string></var><var name="description"><string>Yes on the alert dialog</string></var></struct><struct><var name="key"><string>al_no</string></var><var name="value"><string>Hayır</string></var><var name="description"><string>'No' on the alert dialog</string></var></struct><struct><var name="key"><string>ls_remove_warning_msg</string></var><var name="value"><string>UYARI: Ders kaldırılmak üzere. Bu dersi saklamak istiyor musunuz?</string></var><var name="description"><string>Message for the alert dialog which appears following confirmation dialog for removing a lesson.</string></var></struct><struct><var name="key"><string>check_avail_btn</string></var><var name="value"><string>Kullanılabilirliğini kontrol et.</string></var><var name="description"><string>Check Availability button label</string></var></struct><struct><var name="key"><string>about_popup_title_lbl</string></var><var name="value"><string>{0} hakkında</string></var><var name="description"><string>Title for the About Pop-up window.</string></var></struct><struct><var name="key"><string>about_popup_version_lbl</string></var><var name="value"><string>Sürüm</string></var><var name="description"><string>Label displaying the version no on the About dialog.</string></var></struct><struct><var name="key"><string>about_popup_copyright_lbl</string></var><var name="value"><string>© 2002-2008 {0} Foundation. </string></var><var name="description"><string>Label displaying copyright statement in About dialog.</string></var></struct><struct><var name="key"><string>ls_manage_start_btn_tooltip</string></var><var name="value"><string>Dersi hemen başlat</string></var><var name="description"><string>tool tip message for the start now button in lesson tab under manage lesson section when staff has not yet started the lesson while creating a lesson</string></var></struct><struct><var name="key"><string>gpl_license_url</string></var><var name="value"><string>www.gnu.org/licenses/gpl.txt</string></var><var name="description"><string>URL address for GPL licence.</string></var></struct><struct><var name="key"><string>mtab_learners</string></var><var name="value"><string>Öğrenciler</string></var><var name="description"><string>Monitor Learners tab</string></var></struct><struct><var name="key"><string>ls_learners_lbl</string></var><var name="value"><string>Öğrenciler</string></var><var name="description"><string>Learner label - Lesson details</string></var></struct><struct><var name="key"><string>ls_of_text</string></var><var name="value"><string>in </string></var><var name="description"><string>i.e. 1 of 10 Used for showing how many learners have started</string></var></struct><struct><var name="key"><string>ccm_monitor_activity</string></var><var name="value"><string>Etkinlik izlemeyi aç</string></var><var name="description"><string>Label for Custom Context Monitor Activity</string></var></struct><struct><var name="key"><string>close_mc_tooltip</string></var><var name="value"><string>Simge durumuna küçült</string></var><var name="description"><string>Tooltip message for close button on Branching canvas.</string></var></struct><struct><var name="key"><string>ls_seq_status_define_later</string></var><var name="value"><string>Daha sonra tanımla</string></var><var name="description"><string>Of an Activity: when the content for the Activity must defined in the Lesson (via Monitoring) rather than by the Author</string></var></struct><struct><var name="key"><string>ls_continue_lbl</string></var><var name="value"><string>Hi {1}, düzenlemeyi bitirmediniz.</string></var><var name="description"><string>Continue message label</string></var></struct><struct><var name="key"><string>stream_reference_lbl</string></var><var name="value"><string>LAMS</string></var><var name="description"><string>Reference label for the application stream.</string></var></struct><struct><var name="key"><string>mv_search_default_txt</string></var><var name="value"><string>Anahtar kelime veya sayfa numarası giriniz.</string></var><var name="description"><string>The text that is initially displayed in the search/index text field. Search query corresponds to all or part of a learners' name and page number corresponds to a specific page of learners. The user will enter something and then click on the 'Go' button, after which the results will be displayed.</string></var></struct><struct><var name="key"><string>ls_manage_time_lbl</string></var><var name="value"><string>Zaman (Saat:dakika)</string></var><var name="description"><string>Time fields title - Lesson details (manage section)</string></var></struct><struct><var name="key"><string>ls_seq_status_teacher_branching</string></var><var name="value"><string>Öğretmen seçimli dallanma</string></var><var name="description"><string>A type of branching where the Teacher chooses which learners to add to each branch</string></var></struct><struct><var name="key"><string>ls_seq_status_not_set</string></var><var name="value"><string>Henüz kurulmadı</string></var><var name="description"><string>The value of the sequence's status is not set</string></var></struct><struct><var name="key"><string>al_activity_openContent_invalid</string></var><var name="value"><string>Üzgünüm! Etkinlik sağ menüsündeki Etkinlik içeriği Aç/Düzenle maddesine tıklamadan önce etkinliği seçmek zorundasınız. </string></var><var name="description"><string>alert message when user click Open/Edit Activity Content menu item in context menu before selecting any activity on the canvas</string></var></struct><struct><var name="key"><string>sched_act_lbl</string></var><var name="value"><string>Takvim</string></var><var name="description"><string>Label for schedule gate activity</string></var></struct><struct><var name="key"><string>mnu_file_schedule</string></var><var name="value"><string>Takvim</string></var><var name="description"><string>Menu bar Schedule</string></var></struct><struct><var name="key"><string>mnu_go_schedule</string></var><var name="value"><string>Takvim</string></var><var name="description"><string>Menu bar Go to Schedule Tab</string></var></struct><struct><var name="key"><string>mnu_go_learners</string></var><var name="value"><string>Öğrenciler</string></var><var name="description"><string>Menu bar Go to Learners Tab</string></var></struct><struct><var name="key"><string>ls_manage_schedule_btn</string></var><var name="value"><string>Takvim</string></var><var name="description"><string>Schedule start button - Lesson details (manage section)</string></var></struct><struct><var name="key"><string>synch_act_lbl</string></var><var name="value"><string>Senkronize et</string></var><var name="description"><string>Used as a label for the Synch Gate Activity Type</string></var></struct><struct><var name="key"><string>ws_dlg_location_button</string></var><var name="value"><string>Konum</string></var><var name="description"><string>Workspace dialogue Location btn label</string></var></struct><struct><var name="key"><string>mnu_view_learners</string></var><var name="value"><string>Öğrenciler..</string></var><var name="description"><string>Menu bar Learners</string></var></struct><struct><var name="key"><string>ls_locked_msg_lbl</string></var><var name="value"><string>Üzgünüm, {0} şuan {1} tarafından düzenleniyor.</string></var><var name="description"><string>Warning message on Monitor locked screen.</string></var></struct><struct><var name="key"><string>ls_continue_action_lbl</string></var><var name="value"><string>Devam etmek için {0}'a tıklayınız.</string></var><var name="description"><string>Action label displayed when a user can proceed to Live Edit.</string></var></struct><struct><var name="key"><string>ls_manage_apply_btn_tooltip</string></var><var name="value"><string>Açılır menü ile bu dersin durumunu değiştirir.</string></var><var name="description"><string>tool tip message for the apply button in lesson tab under manage lesson section to change the lesson status</string></var></struct><struct><var name="key"><string>td_desc_text</string></var><var name="value"><string>Bu sekmenin kullanımı akışı tamamlamanızı gerektirmez. Daha fazla bilgi için yardım sayfasına bakınız. Bu özellik tüm işlevleriyle çalışıyor.</string></var><var name="description"><string>Todo tab description</string></var></struct><struct><var name="key"><string>al_confirm_forcecomplete_to_end_of_branching_seq</string></var><var name="value"><string>Öğrenci {0}'ı dallanma sıralamasını sonuna göndermek istediğinizden emin misiniz?</string></var><var name="description"><string>This confirmation dialog appears after a learner icon has been dropped on the finish door within the branching view.</string></var></struct><struct><var name="key"><string>ls_manage_schedule_btn_tooltip</string></var><var name="value"><string>Dersi belirlenen tarihte başlatmak üzere takvim oluşturur.</string></var><var name="description"><string>tool tip message for the schedule button in lesson tab under manage lesson section to shedule the lesson to start of selected date and time</string></var></struct><struct><var name="key"><string>mnu_help_help</string></var><var name="value"><string>İzleme yardım</string></var><var name="description"><string>Menu bar Help item</string></var></struct><struct><var name="key"><string>ws_tree_orgs</string></var><var name="value"><string>Organizasyon</string></var><var name="description"><string>Shown in the top level of the tree in the workspace</string></var></struct><struct><var name="key"><string>staff_group_name</string></var><var name="value"><string>{0} izleyici</string></var><var name="description"><string>Group name for the class's staff group.</string></var></struct><struct><var name="key"><string>al_confirm_live_edit</string></var><var name="value"><string>Çalışırken düzenle'yi açmak üzeresiniz. Devam etmek istiyor musunuz?</string></var><var name="description"><string>Confirm warning (dialog) message displayed when opening Live Edit.</string></var></struct><struct><var name="key"><string>mnu_go_todo</string></var><var name="value"><string>Yap</string></var><var name="description"><string>Menu bar Todo</string></var></struct><struct><var name="key"><string>mtab_todo</string></var><var name="value"><string>Yap</string></var><var name="description"><string>Monitor Todo tab</string></var></struct><struct><var name="key"><string>al_error_forcecomplete_notarget</string></var><var name="value"><string>Lütfen öğrenci {0}'ı bir etkinliğin üzerine veya dersin sonuna bırakınız.</string></var><var name="description"><string>Error Message when learner has been dropped outside of an activity or end of lesson bar at the bottom on the canvas</string></var></struct><struct><var name="key"><string>refresh_btn_tooltip</string></var><var name="value"><string>Öğrenciler için son değişimleri yükler</string></var><var name="description"><string>tool tip message for the refresh button</string></var></struct><struct><var name="key"><string>branch_mapping_dlg_conditions_dgd_lbl</string></var><var name="value"><string>Haritalama</string></var><var name="description"><string>Heading label for Mapping datagrid.</string></var></struct><struct><var name="key"><string>mv_search_error_msg</string></var><var name="value"><string>Lütfen 1 ve {0} arasında bir sayfa sayısı veya anahtar kelime girerek sorgulama yapınız.</string></var><var name="description"><string>This error message appears if the search/index field is blank when the user clicks the 'Go' button.</string></var></struct><struct><var name="key"><string>mv_search_invalid_input_msg</string></var><var name="value"><string>Sayfa numarası 1 ile {0} arasında olmalıdır.</string></var><var name="description"><string>This error message appears if the number entered by the user lies outside the range of viewable pages.</string></var></struct><struct><var name="key"><string>al_confirm_forcecomplete_toactivity</string></var><var name="value"><string>Öğrenci '{0}' ı Etkinlik {1}'i yapmaya zorlamak istediğinizden emin misiniz?</string></var><var name="description"><string>Message to get confirmation from user before send data to server for force complete a learner to the activity it has been dropped</string></var></struct><struct><var name="key"><string>al_error_forcecomplete_invalidactivity</string></var><var name="value"><string>Öğrenci {0}'ı şuanki etkinliğine veya tamamladığı etkinlik {1}'e bıraktınız.</string></var><var name="description"><string>Error message when learner has been dropped on its previous or on its current activity</string></var></struct><struct><var name="key"><string>al_error_forcecomplete_to_different_seq</string></var><var name="value"><string>{0} farklı bir sıralama veya dallanmadaki etkinliğe bırakılamaz.</string></var><var name="description"><string>This alert appears when either: The learner is in a branching sequence and the monitor tries to force complete them to an activity in a different branching sequence, or: the learner is in an optional sequence and the monitor tries to force complete them to an activity in a different optional sequence</string></var></struct><struct><var name="key"><string>ls_win_editclass_staff_lbl</string></var><var name="value"><string>İzleme</string></var><var name="description"><string>Heading for Staff list on Edit Class popup</string></var></struct><struct><var name="key"><string>ls_seq_status_contribution</string></var><var name="value"><string>Katılım</string></var><var name="description"><string>Any 'Contributions' to be made by a monitor, such as editing text for 'Define in Monitor' tasks, marking essay/reports, releasing stop points, etc.</string></var></struct><struct><var name="key"><string>finish_learner_tooltip</string></var><var name="value"><string>Öğrenciyi dersi tamamlamaya zorlamak için öğrenci simgesini bu çubuğa sürükleyiniz ve bırakınız.</string></var><var name="description"><string>Rollover message when user moves their mouse over the end gate bar in monitor tab view</string></var></struct><struct><var name="key"><string>label.grouping.general.instructions.branching</string></var><var name="value"><string>Grubun dallanmasını etkileyeceğinden bu gruplamaya grup ekleyip kaldıramazsınız. Sadece varolan gruplara kullanıcıekleyip kaldırabilirsiniz.</string></var><var name="description"><string>Third instructions paragraph on the chosen branching screen.</string></var></struct><struct><var name="key"><string>ls_sequence_live_edit_btn_tooltip</string></var><var name="value"><string>Bu ders için geçerli tasarımı düzenler.</string></var><var name="description"><string>Tool tip message for Live Edit button</string></var></struct><struct><var name="key"><string>ls_sequence_live_edit_btn</string></var><var name="value"><string>Canlı düzenle</string></var><var name="description"><string>Live Edit button</string></var></struct><struct><var name="key"><string>ls_seq_status_sched_gate</string></var><var name="value"><string>Kapıyı programla</string></var><var name="description"><string>A type of Gate Activity where progress depends on time (start time and/or end time)</string></var></struct><struct><var name="key"><string>ls_seq_status_synch_gate</string></var><var name="value"><string>Senkronize kapısı</string></var><var name="description"><string>A type of Gate Activity where progress depends on all Learners in the Class or Group reaching the activity</string></var></struct><struct><var name="key"><string>ls_status_scheduled_lbl</string></var><var name="value"><string>Zaman çizelgesi oluşturuldu.</string></var><var name="description"><string>Lesson status option - Scheduled (Not Started)</string></var></struct><struct><var name="key"><string>mapped_competences_lbl</string></var><var name="value"><string>Haritalanmış yetkiker</string></var><var name="description"><string>Title for the dialog that shows all competences mapped to an activity</string></var></struct><struct><var name="key"><string>competences_mapped_to_act_lbl</string></var><var name="value"><string>Yetkiler {0}'a haritalandı.</string></var><var name="description"><string>Label in the Competence Mappings dialog to show all the competences mapped to an activity who's name is given by the argument</string></var></struct><struct><var name="key"><string>competence_title_lbl</string></var><var name="value"><string>Başlık</string></var><var name="description"><string>Competence Title label in Mapped Competences dialog</string></var></struct><struct><var name="key"><string>view_competences_in_ld_lbl</string></var><var name="value"><string>Öğrenme tasarımındaki yetkiler: {0}</string></var><var name="description"><string>Label for dialog that shows all the competences in a learning design with a name specified by the argument</string></var></struct><struct><var name="key"><string>competence_desc_lbl</string></var><var name="value"><string>Açıklama</string></var><var name="description"><string>Competence Description label in Mapped Competences dialog</string></var></struct><struct><var name="key"><string>al_ok</string></var><var name="value"><string>Tamam</string></var><var name="description"><string>OK on the alert dialog</string></var></struct><struct><var name="key"><string>order_learners_by_completion_lbl</string></var><var name="value"><string>Dersi tamamlama sürecini öğrenciye göster.</string></var><var name="description"><string>Label for checkbox in index bar in the learners tab to order learners based how far they've progressed through the lesson</string></var></struct><struct><var name="key"><string>ls_manage_presenceEnabled_lbl</string></var><var name="value"><string>Öğrencilerin çevrimiçi kişileri görmesine izin ver.</string></var><var name="description"><string>ls_manage_presenceEnabled_lbl</string></var></struct><struct><var name="key"><string>ls_confirm_presence_enabled</string></var><var name="value"><string>Öğrencileri çevrimiçi kişileri göremeyecekler.</string></var><var name="description"><string>ls_confirm_presence_enabled</string></var></struct><struct><var name="key"><string>ls_confirm_presence_disabled</string></var><var name="value"><string>Öğrencileri çevrimiçi kişileri görebilecekler.</string></var><var name="description"><string>ls_confirm_presence_disabled</string></var></struct><struct><var name="key"><string>al_confirm_forcecomplete_tofinish</string></var><var name="value"><string>Öğrenci {0}'ı dersi bitirmeye zorlamak istediğinizden emin misiniz?</string></var><var name="description"><string>Message to get confirmation from user before sending data to server for force complete to the end of lesson</string></var></struct><struct><var name="key"><string>lbl_num_sequences</string></var><var name="value"><string>{0} - Akışlar</string></var><var name="description"><string>Number of child sequence or Optional Sequences activity shown on canvas.</string></var></struct><struct><var name="key"><string>sys_error_msg_finish</string></var><var name="value"><string>Devam etmek için LAMS tasarımı yeniden başlatmalısınız. Problemin giderilmesinde yardımcı olmak için hata bilgisini kaydetmek ister misiniz?</string></var><var name="description"><string>Common System error message finish paragraph</string></var></struct><struct><var name="key"><string>about_popup_trademark_lbl</string></var><var name="value"><string>{0} is a trademark of {0} Foundation ( {1} ). </string></var><var name="description"><string>Label displaying the trademark statement in the About dialog.</string></var></struct><struct><var name="key"><string>ls_win_learners_heading_class_lbl</string></var><var name="value"><string>Sınıf</string></var><var name="description"><string>Heading on View Learners window panel (learners of the class).</string></var></struct><struct><var name="key"><string>ls_win_learners_heading_activity_lbl</string></var><var name="value"><string>Etkinlik</string></var><var name="description"><string>Heading on View Learners window panel (learners at activity).</string></var></struct><struct><var name="key"><string>learner_plus_tooltip</string></var><var name="value"><string>{0} öğrenci. Tüm listeyi görmek için çift tıklayınız.</string></var><var name="description"><string>Tooltip message displayed when mouse-over the cross icon, displayed when there is a large amount of users at an activity.</string></var></struct></array></var></struct></data></wddxPacket>